pyproject.toml
setup.py
template2/__init__.py
template2.egg-info/PKG-INFO
template2.egg-info/SOURCES.txt
template2.egg-info/dependency_links.txt
template2.egg-info/entry_points.txt
template2.egg-info/requires.txt
template2.egg-info/top_level.txt