Metadata-Version: 2.4
Name: template2
Version: 6.0.0rc8
Home-page: https://yourlabs.io/oss/cli2
Author: James Pic
Author-email: jamespic@gmail.com
License: MIT
Keywords: cli
Requires-Python: >=3.6
Requires-Dist: cli2
Requires-Dist: jinja2
Dynamic: author
Dynamic: author-email
Dynamic: home-page
Dynamic: keywords
Dynamic: license
Dynamic: requires-dist
Dynamic: requires-python
